barkus/__init__.py
barkus/functions/__init__.py
barkus/functions/toolkit/__init__.py
barkus/functions/toolkit/authenticator.py
barkus/functions/toolkit/cloud_client_manager.py
barkus/functions/toolkit/parse_request.py
barkus/functions/toolkit/publish_to_topic.py
barkus/functions/toolkit/collection/__init__.py
barkus/functions/toolkit/decorators/__init__.py
barkus/functions/toolkit/decorators/log_decorator.py
barkus/functions/toolkit/decorators/main_decorator.py
barkus/functions/toolkit/errors/__init__.py
barkus_func_toolkit-0.0.8.dist-info/LICENSE
barkus_func_toolkit-0.0.8.dist-info/METADATA
barkus_func_toolkit-0.0.8.dist-info/WHEEL
barkus_func_toolkit-0.0.8.dist-info/top_level.txt
barkus_func_toolkit-0.0.8.dist-info/RECORD
